setup.py
HNBEX.egg-info/PKG-INFO
HNBEX.egg-info/SOURCES.txt
HNBEX.egg-info/dependency_links.txt
HNBEX.egg-info/requires.txt
HNBEX.egg-info/top_level.txt
hnbex/__init__.py
hnbex.egg-info/PKG-INFO
hnbex.egg-info/SOURCES.txt
hnbex.egg-info/dependency_links.txt
hnbex.egg-info/requires.txt
hnbex.egg-info/top_level.txt