Metadata-Version: 1.1
Name: hnbex
Version: 0.0.1
Summary: A Python package for accessing hnbex.eu service
Home-page: https://github.com/dobarkod/hnbex-python
Author: Amalia Souček
Author-email: amalia.soucek@dobarkod.hr
License: MIT
Platform: UNKNOWN
Classifier: Environment :: Web Environment
Classifier: Intended Audience :: Developers
Classifier: License :: OSI Approved :: MIT License
Classifier: Programming Language :: Python
Classifier: Programming Language :: Python :: 2
Classifier: Programming Language :: Python :: 3
Classifier: Topic :: Software Development :: Libraries :: Python Modules
